ext_pathlib.py
ext_pathlib-2.1.2.dist-info/METADATA
ext_pathlib-2.1.2.dist-info/WHEEL
ext_pathlib-2.1.2.dist-info/top_level.txt
ext_pathlib-2.1.2.dist-info/RECORD
