Metadata-Version: 2.1
Name: ext-pathlib
Version: 2.1.2
Summary: Extended Pathlib module.
Home-page: UNKNOWN
License: UNKNOWN
Platform: UNKNOWN
